Metadata-Version: 2.4
Name: llm-tools-datasette
Version: 0.1
Summary: Expose Datasette instances to LLM as a tool
Author: Simon Willison
License-Expression: Apache-2.0
Project-URL: Homepage, https://github.com/simonw/llm-tools-datasette
Project-URL: Changelog, https://github.com/simonw/llm-tools-datasette/releases
Project-URL: Issues, https://github.com/simonw/llm-tools-datasette/issues
Project-URL: CI, https://github.com/simonw/llm-tools-datasette/actions
Requires-Python: >=3.9
License-File: LICENSE
Requires-Dist: llm>=0.26
Provides-Extra: test
Requires-Dist: pytest; extra == "test"
Requires-Dist: llm-echo>=0.3a1; extra == "test"
Requires-Dist: pytest-httpx; extra == "test"
Dynamic: license-file
